overrun-0.1.0.dist-info/METADATA
overrun-0.1.0.dist-info/WHEEL
overrun-0.1.0.dist-info/entry_points.txt
overrun/__init__.py
overrun/cli.py
overrun-0.1.0.dist-info/RECORD
