Metadata-Version: 2.1
Name: overrun
Version: 0.1.0
Summary: Task runner for persistent local development environments
Author-Email: Terry Kerr <terry@idletea.net>
License: MIT
Requires-Python: >=3.12
